TEPP/__init__.py
TEPP/decl.py
tepp-1.0.0.1.dist-info/LICENSE
tepp-1.0.0.1.dist-info/METADATA
tepp-1.0.0.1.dist-info/WHEEL
tepp-1.0.0.1.dist-info/RECORD
